nbit-0.1.dist-info/DESCRIPTION.rst
nbit-0.1.dist-info/RECORD
nbit-0.1.dist-info/METADATA
nbit-0.1.dist-info/WHEEL
nbit-0.1.dist-info/metadata.json
nbit-0.1.dist-info/entry_points.txt
nbit-0.1.dist-info/top_level.txt
nbit/nbit.py
nbit/__init__.py
