Metadata-Version: 2.0
Name: nbit
Version: 0.1
Summary: Build tool for node.js projects
Home-page: https://github.com/divergence082/NBit
Author: Valeria Lepina
Author-email: divergence082@gmail.com
License: MIT
Keywords: node nodejs js node.js build bootstrap-project google-closure-compiler
Platform: UNKNOWN
Classifier: Development Status :: 1 - Planning
Classifier: Intended Audience :: Developers
Classifier: Topic :: Software Development :: Build Tools
Classifier: Programming Language :: Python
